<?xml version="1.0" encoding="utf-8"?>

<config>
  <contentFilters>
    <contentFilter mimeTypeMatch="text/html" uriMatch=".*">
      <replacements>
        <replacement from='href="/image/' to='href="/rportal/image/' />
        <replacement from='src="/image/' to='src="/rportal/image/' />
        <replacement from='url("/image/' to='url("/rportal/image/' />
        <replacement from='url(/image/' to='url(/rportal/image/' />
        
        <replacement from='href="/html/' to='href="/rportal/html/' />
        <replacement from='src="/html/' to='src="/rportal/html/' />
        <replacement from='url("/html/' to='url("/rportal/html/' />
        <replacement from='url(/html/' to='url(/rportal/html/' />
        
        <replacement from="http://localhost:8080/" to="/" type="replace-first" />
        
      </replacements>
    </contentFilter>
  </contentFilters>

  <responseHeaderFilters>
    <responseHeaderFilter header="Location">
      <replacements>
        <replacement from="http://localhost:8080/" to="/" />
      </replacements>
    </responseHeaderFilter>
    <responseHeaderFilter header="Set-Cookie">
      <replacements>
        <replacement from=".*" to="" type="replace-all-regex" />
      </replacements>
    </responseHeaderFilter>
  </responseHeaderFilters>
  
  <requestHeaderFilters>
    <requestHeaderFilter header="Cookie">
      <replacements>
        <replacement from="GUEST_LANGUAGE_ID=(.*?);" to="" type="replace-first-regex" />
      </replacements>
    </requestHeaderFilter>
  </requestHeaderFilters>
  
  <uriFilters>
    <uriFilter uriMatch=".*lightbulb.gif">
      <replacements>
        <replacement to='request.session.setAttribute("foo", "bar");return request.requestURI + "?foo=bar&amp;boo=baz;"' type="mvel" />
      </replacements>
    </uriFilter>
  </uriFilters>
    
</config>
